workflow_tools/__init__.py
workflow_tools/cli.py
workflow_tools/const.py
workflow_tools/secret.py
workflow_tools/template.py
workflow_tools-0.6.0.dist-info/LICENSE
workflow_tools-0.6.0.dist-info/METADATA
workflow_tools-0.6.0.dist-info/WHEEL
workflow_tools-0.6.0.dist-info/entry_points.txt
workflow_tools-0.6.0.dist-info/top_level.txt
workflow_tools-0.6.0.dist-info/zip-safe
workflow_tools-0.6.0.dist-info/RECORD
