Metadata-Version: 2.1
Name: workflow-tools
Version: 0.6.0
Summary: CLI tools for GitHub Actions
Home-page: https://github.com/anna-money/workflow-tools
Author: Absolutely No Nonsense Admin Ltd.
Author-email: hello@anna.money
License: Apache License 2.0
Platform: UNKNOWN
Classifier: Development Status :: 4 - Beta
Classifier: Programming Language :: Python
Classifier: Intended Audience :: Developers
Classifier: Intended Audience :: Information Technology
Classifier: Intended Audience :: System Administrators
Classifier: License :: OSI Approved :: Apache Software License
Classifier: Operating System :: Unix
Classifier: Operating System :: POSIX :: Linux
Classifier: Environment :: Console
Classifier: Environment :: MacOS X
Classifier: Topic :: Internet
Requires-Python: >=2.7, !=3.0.*, !=3.1.*, !=3.2.*, <4
Requires-Dist: Jinja2 (>=2.11.1)
Requires-Dist: Click (<8.0,>=7.0)
Requires-Dist: PyNaCl (<2.0,>=1.3.0)
Requires-Dist: requests (<3.0,>=2.22.0)
